[
  {
    "timestamp": 1754380350.7816198,
    "cpu_percent": 21.1,
    "memory_mb": 10122.25390625,
    "cache_hit_rate": 0.0,
    "active_threads": 2,
    "response_time_ms": 0.0,
    "operation_type": "system_monitor"
  },
  {
    "timestamp": 1754380361.7897978,
    "cpu_percent": 23.8,
    "memory_mb": 10161.56640625,
    "cache_hit_rate": 0.0,
    "active_threads": 2,
    "response_time_ms": 0.0,
    "operation_type": "system_monitor"
  },
  {
    "timestamp": 1754380372.7985163,
    "cpu_percent": 19.1,
    "memory_mb": 10159.30859375,
    "cache_hit_rate": 0.0,
    "active_threads": 2,
    "response_time_ms": 0.0,
    "operation_type": "system_monitor"
  },
  {
    "timestamp": 1754380383.8050532,
    "cpu_percent": 15.5,
    "memory_mb": 10529.86328125,
    "cache_hit_rate": 0.0,
    "active_threads": 2,
    "response_time_ms": 0.0,
    "operation_type": "system_monitor"
  },
  {
    "timestamp": 1754380394.8121212,
    "cpu_percent": 30.7,
    "memory_mb": 10677.55859375,
    "cache_hit_rate": 0.0,
    "active_threads": 2,
    "response_time_ms": 0.0,
    "operation_type": "system_monitor"
  },
  {
    "timestamp": 1754380405.8182526,
    "cpu_percent": 15.3,
    "memory_mb": 10990.61328125,
    "cache_hit_rate": 0.0,
    "active_threads": 2,
    "response_time_ms": 0.0,
    "operation_type": "system_monitor"
  },
  {
    "timestamp": 1754380416.8261113,
    "cpu_percent": 25.3,
    "memory_mb": 11283.64453125,
    "cache_hit_rate": 0.0,
    "active_threads": 2,
    "response_time_ms": 0.0,
    "operation_type": "system_monitor"
  },
  {
    "timestamp": 1754380427.8322256,
    "cpu_percent": 24.7,
    "memory_mb": 11288.01171875,
    "cache_hit_rate": 0.0,
    "active_threads": 2,
    "response_time_ms": 0.0,
    "operation_type": "system_monitor"
  },
  {
    "timestamp": 1754380438.8397937,
    "cpu_percent": 12.9,
    "memory_mb": 11056.67578125,
    "cache_hit_rate": 0.0,
    "active_threads": 2,
    "response_time_ms": 0.0,
    "operation_type": "system_monitor"
  },
  {
    "timestamp": 1754380449.8468914,
    "cpu_percent": 18.4,
    "memory_mb": 11118.3125,
    "cache_hit_rate": 0.0,
    "active_threads": 2,
    "response_time_ms": 0.0,
    "operation_type": "system_monitor"
  }
]